{
  "word_count": 6616,
  "processed_language": "en",
  "personality": [
    {
      "trait_id": "big5_openness",
      "name": "Openness",
      "category": "personality",
      "percentile": 0.9721333321887244,
      "raw_score": 0.8097314078309014,
      "significant": true,
      "children": [
        {
          "trait_id": "facet_adventurousness",
          "name": "Adventurousness",
          "category": "personality",
          "percentile": 0.937422176940695,
          "raw_score": 0.5593578546874299,
          "significant": true
        },
        {
          "trait_id": "facet_artistic_interests",
          "name": "Artistic interests",
          "category": "personality",
          "percentile": 0.4897012075702125,
          "raw_score": 0.6640177449425922,
          "significant": true
        },
        {
          "trait_id": "facet_emotionality",
          "name": "Emotionality",
          "category": "personality",
          "percentile": 0.16053550085714846,
          "raw_score": 0.607741851070387,
          "significant": true
        },
        {
          "trait_id": "facet_imagination",
          "name": "Imagination",
          "category": "personality",
          "percentile": 0.028893146175534956,
          "raw_score": 0.6406183231848177,
          "significant": true
        },
        {
          "trait_id": "facet_intellect",
          "name": "Intellect",
          "category": "personality",
          "percentile": 0.9880343243962579,
          "raw_score": 0.7117735523891354,
          "significant": true
        },
        {
          "trait_id": "facet_liberalism",
          "name": "Authority-challenging",
          "category": "personality",
          "percentile": 0.9297214705960668,
          "raw_score": 0.590455420949378,
          "significant": true
        }
      ]
    },
    {
      "trait_id": "big5_conscientiousness",
      "name": "Conscientiousness",
      "category": "personality",
      "percentile": 0.8244977611868503,
      "raw_score": 0.6715502545943872,
      "significant": true,
      "children": [
        {
          "trait_id": "facet_achievement_striving",
          "name": "Achievement striving",
          "category": "personality",
          "percentile": 0.8606868310602607,
          "raw_score": 0.7457590297957091,
          "significant": true
        },
        {
          "trait_id": "facet_cautiousness",
          "name": "Cautiousness",
          "category": "personality",
          "percentile": 0.9775053098158853,
          "raw_score": 0.6190246014846856,
          "significant": true
        },
        {
          "trait_id": "facet_dutifulness",
          "name": "Dutifulness",
          "category": "personality",
          "percentile": 0.7963990056893284,
          "raw_score": 0.6791980669813346,
          "significant": true
        },
        {
          "trait_id": "facet_orderliness",
          "name": "Orderliness",
          "category": "personality",
          "percentile": 0.26994378382711287,
          "raw_score": 0.4740772035907165,
          "significant": true
        },
        {
          "trait_id": "facet_self_discipline",
          "name": "Self-discipline",
          "category": "personality",
          "percentile": 0.8510118083944946,
          "raw_score": 0.6202324754523307,
          "significant": true
        },
        {
          "trait_id": "facet_self_efficacy",
          "name": "Self-efficacy",
          "category": "personality",
          "percentile": 0.672400254258314,
          "raw_score": 0.7688041070014859,
          "significant": true
        }
      ]
    },
    {
      "trait_id": "big5_extraversion",
      "name": "Extraversion",
      "category": "personality",
      "percentile": 0.5396282099201863,
      "raw_score": 0.5554460611786882,
      "significant": true,
      "children": [
        {
          "trait_id": "facet_activity_level",
          "name": "Activity level",
          "category": "personality",
          "percentile": 0.9582031571210814,
          "raw_score": 0.6289118994058243,
          "significant": true
        },
        {
          "trait_id": "facet_assertiveness",
          "name": "Assertiveness",
          "category": "personality",
          "percentile": 0.9664293035203425,
          "raw_score": 0.7355772554419917,
          "significant": true
        },
        {
          "trait_id": "facet_cheerfulness",
          "name": "Cheerfulness",
          "category": "personality",
          "percentile": 0.37548573150849474,
          "raw_score": 0.6074880427974835,
          "significant": true
        },
        {
          "trait_id": "facet_excitement_seeking",
          "name": "Excitement-seeking",
          "category": "personality",
          "percentile": 0.03595246074953484,
          "raw_score": 0.5272960318164681,
          "significant": true
        },
        {
          "trait_id": "facet_friendliness",
          "name": "Outgoing",
          "category": "personality",
          "percentile": 0.8251053406151178,
          "raw_score": 0.6073839929069194,
          "significant": true
        },
        {
          "trait_id": "facet_gregariousness",
          "name": "Gregariousness",
          "category": "personality",
          "percentile": 0.4929350887225254,
          "raw_score": 0.45243299524409986,
          "significant": true
        }
      ]
    },
    {
      "trait_id": "big5_agreeableness",
      "name": "Agreeableness",
      "category": "personality",
      "percentile": 0.1616163392678956,
      "raw_score": 0.7029274247780789,
      "significant": true,
      "children": [
        {
          "trait_id": "facet_altruism",
          "name": "Altruism",
          "category": "personality",
          "percentile": 0.8240828012697967,
          "raw_score": 0.7377510039922113,
          "significant": true
        },
        {
          "trait_id": "facet_cooperation",
          "name": "Cooperation",
          "category": "personality",
          "percentile": 0.9175496082671138,
          "raw_score": 0.66305959732226,
          "significant": true
        },
        {
          "trait_id": "facet_modesty",
          "name": "Modesty",
          "category": "personality",
          "percentile": 0.4438152901132573,
          "raw_score": 0.44091962878333907,
          "significant": true
        },
        {
          "trait_id": "facet_morality",
          "name": "Uncompromising",
          "category": "personality",
          "percentile": 0.8901149855695046,
          "raw_score": 0.6837123776163294,
          "significant": true
        },
        {
          "trait_id": "facet_sympathy",
          "name": "Sympathy",
          "category": "personality",
          "percentile": 0.9713771339688138,
          "raw_score": 0.7360831908226042,
          "significant": true
        },
        {
          "trait_id": "facet_trust",
          "name": "Trust",
          "category": "personality",
          "percentile": 0.8829854080282981,
          "raw_score": 0.6348282794770849,
          "significant": true
        }
      ]
    },
    {
      "trait_id": "big5_neuroticism",
      "name": "Emotional range",
      "category": "personality",
      "percentile": 0.8710772214675616,
      "raw_score": 0.5311503040500878,
      "significant": true,
      "children": [
        {
          "trait_id": "facet_anger",
          "name": "Fiery",
          "category": "personality",
          "percentile": 0.011119639892276267,
          "raw_score": 0.4106899968593205,
          "significant": true
        },
        {
          "trait_id": "facet_anxiety",
          "name": "Prone to worry",
          "category": "personality",
          "percentile": 0.016476192448367455,
          "raw_score": 0.4486705120924622,
          "significant": true
        },
        {
          "trait_id": "facet_depression",
          "name": "Melancholy",
          "category": "personality",
          "percentile": 0.19381512789355715,
          "raw_score": 0.39371966489529353,
          "significant": true
        },
        {
          "trait_id": "facet_immoderation",
          "name": "Immoderation",
          "category": "personality",
          "percentile": 0.26439454863651185,
          "raw_score": 0.47638404600887674,
          "significant": true
        },
        {
          "trait_id": "facet_self_consciousness",
          "name": "Self-consciousness",
          "category": "personality",
          "percentile": 0.06540178795496743,
          "raw_score": 0.4672097386466515,
          "significant": true
        },
        {
          "trait_id": "facet_vulnerability",
          "name": "Susceptible to stress",
          "category": "personality",
          "percentile": 0.04143308066141288,
          "raw_score": 0.35712785427081506,
          "significant": true
        }
      ]
    }
  ],
  "needs": [
    {
      "trait_id": "need_challenge",
      "name": "Challenge",
      "category": "needs",
      "percentile": 0.19363325397236614,
      "raw_score": 0.6930089696786689,
      "significant": true
    },
    {
      "trait_id": "need_closeness",
      "name": "Closeness",
      "category": "needs",
      "percentile": 0.07245644245012867,
      "raw_score": 0.728657098284283,
      "significant": true
    },
    {
      "trait_id": "need_curiosity",
      "name": "Curiosity",
      "category": "needs",
      "percentile": 0.23482576426326335,
      "raw_score": 0.7976203701453656,
      "significant": true
    },
    {
      "trait_id": "need_excitement",
      "name": "Excitement",
      "category": "needs",
      "percentile": 0.08777560368896198,
      "raw_score": 0.5776032137101381,
      "significant": true
    },
    {
      "trait_id": "need_harmony",
      "name": "Harmony",
      "category": "needs",
      "percentile": 0.00969870817686247,
      "raw_score": 0.7285329851770682,
      "significant": true
    },
    {
      "trait_id": "need_ideal",
      "name": "Ideal",
      "category": "needs",
      "percentile": 0.03620409055929752,
      "raw_score": 0.6056791736819886,
      "significant": true
    },
    {
      "trait_id": "need_liberty",
      "name": "Liberty",
      "category": "needs",
      "percentile": 0.05771626511344019,
      "raw_score": 0.677537631082472,
      "significant": true
    },
    {
      "trait_id": "need_love",
      "name": "Love",
      "category": "needs",
      "percentile": 0.007853376721228766,
      "raw_score": 0.6511483789261857,
      "significant": true
    },
    {
      "trait_id": "need_practicality",
      "name": "Practicality",
      "category": "needs",
      "percentile": 0.10394203411281977,
      "raw_score": 0.70056315416956,
      "significant": true
    },
    {
      "trait_id": "need_self_expression",
      "name": "Self-expression",
      "category": "needs",
      "percentile": 0.00798792170179291,
      "raw_score": 0.5919218676677155,
      "significant": true
    },
    {
      "trait_id": "need_stability",
      "name": "Stability",
      "category": "needs",
      "percentile": 0.054899460217409435,
      "raw_score": 0.6835225504951236,
      "significant": true
    },
    {
      "trait_id": "need_structure",
      "name": "Structure",
      "category": "needs",
      "percentile": 0.7711007178963347,
      "raw_score": 0.7161973529186808,
      "significant": true
    }
  ],
  "values": [
    {
      "trait_id": "value_conservation",
      "name": "Conservation",
      "category": "values",
      "percentile": 0.033096543270296874,
      "raw_score": 0.5826876359789319,
      "significant": true
    },
    {
      "trait_id": "value_openness_to_change",
      "name": "Openness to change",
      "category": "values",
      "percentile": 0.581153513282999,
      "raw_score": 0.7921672537727373,
      "significant": true
    },
    {
      "trait_id": "value_hedonism",
      "name": "Hedonism",
      "category": "values",
      "percentile": 0.015214726948840795,
      "raw_score": 0.5998832167392123,
      "significant": true
    },
    {
      "trait_id": "value_self_enhancement",
      "name": "Self-enhancement",
      "category": "values",
      "percentile": 0.05846515902708249,
      "raw_score": 0.6375482495402087,
      "significant": true
    },
    {
      "trait_id": "value_self_transcendence",
      "name": "Self-transcendence",
      "category": "values",
      "percentile": 0.05922942695799999,
      "raw_score": 0.8075291451124891,
      "significant": true
    }
  ],
  "warnings": []
}