{
  "word_count": 2661,
  "processed_language": "en",
  "personality": [
    {
      "trait_id": "big5_openness",
      "name": "Openness",
      "category": "personality",
      "percentile": 0.9912623899835944,
      "raw_score": 0.8245275225968615,
      "significant": true,
      "children": [
        {
          "trait_id": "facet_adventurousness",
          "name": "Adventurousness",
          "category": "personality",
          "percentile": 0.8005452252036167,
          "raw_score": 0.5348201501544363,
          "significant": true
        },
        {
          "trait_id": "facet_artistic_interests",
          "name": "Artistic interests",
          "category": "personality",
          "percentile": 0.8521756188104592,
          "raw_score": 0.7182671754118521,
          "significant": true
        },
        {
          "trait_id": "facet_emotionality",
          "name": "Emotionality",
          "category": "personality",
          "percentile": 0.5603149955383305,
          "raw_score": 0.6543824611554486,
          "significant": true
        },
        {
          "trait_id": "facet_imagination",
          "name": "Imagination",
          "category": "personality",
          "percentile": 0.20824154007537216,
          "raw_score": 0.6944996519291553,
          "significant": true
        },
        {
          "trait_id": "facet_intellect",
          "name": "Intellect",
          "category": "personality",
          "percentile": 0.9988570733424116,
          "raw_score": 0.7484376901609301,
          "significant": true
        },
        {
          "trait_id": "facet_liberalism",
          "name": "Authority-challenging",
          "category": "personality",
          "percentile": 0.991160228568242,
          "raw_score": 0.6357119128131414,
          "significant": true
        }
      ]
    },
    {
      "trait_id": "big5_conscientiousness",
      "name": "Conscientiousness",
      "category": "personality",
      "percentile": 0.6629540769858115,
      "raw_score": 0.6476652952621306,
      "significant": true,
      "children": [
        {
          "trait_id": "facet_achievement_striving",
          "name": "Achievement striving",
          "category": "personality",
          "percentile": 0.5866727740941156,
          "raw_score": 0.6999929915682732,
          "significant": true
        },
        {
          "trait_id": "facet_cautiousness",
          "name": "Cautiousness",
          "category": "personality",
          "percentile": 0.9844401764152202,
          "raw_score": 0.6285430137991491,
          "significant": true
        },
        {
          "trait_id": "facet_dutifulness",
          "name": "Dutifulness",
          "category": "personality",
          "percentile": 0.8326846632842274,
          "raw_score": 0.682528680774537,
          "significant": true
        },
        {
          "trait_id": "facet_orderliness",
          "name": "Orderliness",
          "category": "personality",
          "percentile": 0.2368643320486966,
          "raw_score": 0.47068885760620993,
          "significant": true
        },
        {
          "trait_id": "facet_self_discipline",
          "name": "Self-discipline",
          "category": "personality",
          "percentile": 0.49589725708746063,
          "raw_score": 0.5701635716654717,
          "significant": true
        },
        {
          "trait_id": "facet_self_efficacy",
          "name": "Self-efficacy",
          "category": "personality",
          "percentile": 0.3516075314509822,
          "raw_score": 0.7397011901847773,
          "significant": true
        }
      ]
    },
    {
      "trait_id": "big5_extraversion",
      "name": "Extraversion",
      "category": "personality",
      "percentile": 0.3111953010994777,
      "raw_score": 0.5290305913099006,
      "significant": true,
      "children": [
        {
          "trait_id": "facet_activity_level",
          "name": "Activity level",
          "category": "personality",
          "percentile": 0.7305654659428614,
          "raw_score": 0.5718237774639866,
          "significant": true
        },
        {
          "trait_id": "facet_assertiveness",
          "name": "Assertiveness",
          "category": "personality",
          "percentile": 0.8057972309297068,
          "raw_score": 0.6871759929052788,
          "significant": true
        },
        {
          "trait_id": "facet_cheerfulness",
          "name": "Cheerfulness",
          "category": "personality",
          "percentile": 0.2368456309955319,
          "raw_score": 0.5940936699198399,
          "significant": true
        },
        {
          "trait_id": "facet_excitement_seeking",
          "name": "Excitement-seeking",
          "category": "personality",
          "percentile": 0.05206045729201636,
          "raw_score": 0.5346958731208014,
          "significant": true
        },
        {
          "trait_id": "facet_friendliness",
          "name": "Outgoing",
          "category": "personality",
          "percentile": 0.5389938130042333,
          "raw_score": 0.5653988282315421,
          "significant": true
        },
        {
          "trait_id": "facet_gregariousness",
          "name": "Gregariousness",
          "category": "personality",
          "percentile": 0.2110026396369955,
          "raw_score": 0.41206353450669025,
          "significant": true
        }
      ]
    },
    {
      "trait_id": "big5_agreeableness",
      "name": "Agreeableness",
      "category": "personality",
      "percentile": 0.30022055236046835,
      "raw_score": 0.7213763357075467,
      "significant": true,
      "children": [
        {
          "trait_id": "facet_altruism",
          "name": "Altruism",
          "category": "personality",
          "percentile": 0.8549833501144217,
          "raw_score": 0.7422066642071946,
          "significant": true
        },
        {
          "trait_id": "facet_cooperation",
          "name": "Cooperation",
          "category": "personality",
          "percentile": 0.9572932601648022,
          "raw_score": 0.6830213297721589,
          "significant": true
        },
        {
          "trait_id": "facet_modesty",
          "name": "Modesty",
          "category": "personality",
          "percentile": 0.4042461189168174,
          "raw_score": 0.43558657833618764,
          "significant": true
        },
        {
          "trait_id": "facet_morality",
          "name": "Uncompromising",
          "category": "personality",
          "percentile": 0.8788097165877414,
          "raw_score": 0.6809718029225611,
          "significant": true
        },
        {
          "trait_id": "facet_sympathy",
          "name": "Sympathy",
          "category": "personality",
          "percentile": 0.9855897896218053,
          "raw_score": 0.7469468235667235,
          "significant": true
        },
        {
          "trait_id": "facet_trust",
          "name": "Trust",
          "category": "personality",
          "percentile": 0.883383946704653,
          "raw_score": 0.6349119317899987,
          "significant": true
        }
      ]
    },
    {
      "trait_id": "big5_neuroticism",
      "name": "Emotional range",
      "category": "personality",
      "percentile": 0.5964097006617386,
      "raw_score": 0.4811241524246913,
      "significant": true,
      "children": [
        {
          "trait_id": "facet_anger",
          "name": "Fiery",
          "category": "personality",
          "percentile": 0.017722032883969674,
          "raw_score": 0.4206979063382763,
          "significant": true
        },
        {
          "trait_id": "facet_anxiety",
          "name": "Prone to worry",
          "category": "personality",
          "percentile": 0.08289303997589487,
          "raw_score": 0.4995994886038666,
          "significant": true
        },
        {
          "trait_id": "facet_depression",
          "name": "Melancholy",
          "category": "personality",
          "percentile": 0.3278743065058971,
          "raw_score": 0.4202033651134243,
          "significant": true
        },
        {
          "trait_id": "facet_immoderation",
          "name": "Immoderation",
          "category": "personality",
          "percentile": 0.29514991728929174,
          "raw_score": 0.47989902968844556,
          "significant": true
        },
        {
          "trait_id": "facet_self_consciousness",
          "name": "Self-consciousness",
          "category": "personality",
          "percentile": 0.3518828544817476,
          "raw_score": 0.5267064349365733,
          "significant": true
        },
        {
          "trait_id": "facet_vulnerability",
          "name": "Susceptible to stress",
          "category": "personality",
          "percentile": 0.18480168575727113,
          "raw_score": 0.41045902790617717,
          "significant": true
        }
      ]
    }
  ],
  "needs": [
    {
      "trait_id": "need_challenge",
      "name": "Challenge",
      "category": "needs",
      "percentile": 0.1497807413761953,
      "raw_score": 0.6852596391738961,
      "significant": true
    },
    {
      "trait_id": "need_closeness",
      "name": "Closeness",
      "category": "needs",
      "percentile": 0.14125340961885902,
      "raw_score": 0.7456585812364181,
      "significant": true
    },
    {
      "trait_id": "need_curiosity",
      "name": "Curiosity",
      "category": "needs",
      "percentile": 0.5643540443384687,
      "raw_score": 0.8209143837155526,
      "significant": true
    },
    {
      "trait_id": "need_excitement",
      "name": "Excitement",
      "category": "needs",
      "percentile": 0.031214939782135742,
      "raw_score": 0.5371984449023666,
      "significant": true
    },
    {
      "trait_id": "need_harmony",
      "name": "Harmony",
      "category": "needs",
      "percentile": 0.047810695402680625,
      "raw_score": 0.7517145072286894,
      "significant": true
    },
    {
      "trait_id": "need_ideal",
      "name": "Ideal",
      "category": "needs",
      "percentile": 0.10744048613308577,
      "raw_score": 0.6321150909355219,
      "significant": true
    },
    {
      "trait_id": "need_liberty",
      "name": "Liberty",
      "category": "needs",
      "percentile": 0.0491276167547135,
      "raw_score": 0.6745731127460031,
      "significant": true
    },
    {
      "trait_id": "need_love",
      "name": "Love",
      "category": "needs",
      "percentile": 0.060316580788893015,
      "raw_score": 0.6931557961355737,
      "significant": true
    },
    {
      "trait_id": "need_practicality",
      "name": "Practicality",
      "category": "needs",
      "percentile": 0.07280668093461251,
      "raw_score": 0.6963328513251942,
      "significant": true
    },
    {
      "trait_id": "need_self_expression",
      "name": "Self-expression",
      "category": "needs",
      "percentile": 0.02697223393630166,
      "raw_score": 0.6085554271531113,
      "significant": true
    },
    {
      "trait_id": "need_stability",
      "name": "Stability",
      "category": "needs",
      "percentile": 0.04115159633545579,
      "raw_score": 0.6791156125680675,
      "significant": true
    },
    {
      "trait_id": "need_structure",
      "name": "Structure",
      "category": "needs",
      "percentile": 0.4022797001555734,
      "raw_score": 0.6893734145200077,
      "significant": true
    }
  ],
  "values": [
    {
      "trait_id": "value_conservation",
      "name": "Conservation",
      "category": "values",
      "percentile": 0.029305958096144225,
      "raw_score": 0.5802558705299885,
      "significant": true
    },
    {
      "trait_id": "value_openness_to_change",
      "name": "Openness to change",
      "category": "values",
      "percentile": 0.434952047035125,
      "raw_score": 0.7779525867216616,
      "significant": true
    },
    {
      "trait_id": "value_hedonism",
      "name": "Hedonism",
      "category": "values",
      "percentile": 0.04371272759381367,
      "raw_score": 0.6289784206705756,
      "significant": true
    },
    {
      "trait_id": "value_self_enhancement",
      "name": "Self-enhancement",
      "category": "values",
      "percentile": 0.0675089716333897,
      "raw_score": 0.6407590793284593,
      "significant": true
    },
    {
      "trait_id": "value_self_transcendence",
      "name": "Self-transcendence",
      "category": "values",
      "percentile": 0.12859804042788586,
      "raw_score": 0.814504070215474,
      "significant": true
    }
  ],
  "warnings": []
}