{
  "word_count": 1156,
  "processed_language": "en",
  "personality": [
    {
      "trait_id": "big5_openness",
      "name": "Openness",
      "category": "personality",
      "percentile": 0.9907102009805899,
      "raw_score": 0.8238029928817223,
      "significant": true,
      "children": [
        {
          "trait_id": "facet_adventurousness",
          "name": "Adventurousness",
          "category": "personality",
          "percentile": 0.9070218769423971,
          "raw_score": 0.5518586850910959,
          "significant": true
        },
        {
          "trait_id": "facet_artistic_interests",
          "name": "Artistic interests",
          "category": "personality",
          "percentile": 0.8544079837878449,
          "raw_score": 0.7187591197669254,
          "significant": true
        },
        {
          "trait_id": "facet_emotionality",
          "name": "Emotionality",
          "category": "personality",
          "percentile": 0.6146506508675247,
          "raw_score": 0.6600775841031012,
          "significant": true
        },
        {
          "trait_id": "facet_imagination",
          "name": "Imagination",
          "category": "personality",
          "percentile": 0.17799170337626435,
          "raw_score": 0.6890106859923226,
          "significant": true
        },
        {
          "trait_id": "facet_intellect",
          "name": "Intellect",
          "category": "personality",
          "percentile": 0.999505868215042,
          "raw_score": 0.7597090326223095,
          "significant": true
        },
        {
          "trait_id": "facet_liberalism",
          "name": "Authority-challenging",
          "category": "personality",
          "percentile": 0.9938248065411748,
          "raw_score": 0.6422449277178143,
          "significant": true
        }
      ]
    },
    {
      "trait_id": "big5_conscientiousness",
      "name": "Conscientiousness",
      "category": "personality",
      "percentile": 0.718046708355862,
      "raw_score": 0.6549650456551569,
      "significant": true,
      "children": [
        {
          "trait_id": "facet_achievement_striving",
          "name": "Achievement striving",
          "category": "personality",
          "percentile": 0.8784965240523652,
          "raw_score": 0.7502113169044942,
          "significant": true
        },
        {
          "trait_id": "facet_cautiousness",
          "name": "Cautiousness",
          "category": "personality",
          "percentile": 0.9875575199041509,
          "raw_score": 0.634075607795775,
          "significant": true
        },
        {
          "trait_id": "facet_dutifulness",
          "name": "Dutifulness",
          "category": "personality",
          "percentile": 0.8284439473647551,
          "raw_score": 0.6821173895475372,
          "significant": true
        },
        {
          "trait_id": "facet_orderliness",
          "name": "Orderliness",
          "category": "personality",
          "percentile": 0.3587513123101096,
          "raw_score": 0.4823049668679458,
          "significant": true
        },
        {
          "trait_id": "facet_self_discipline",
          "name": "Self-discipline",
          "category": "personality",
          "percentile": 0.7052382092439227,
          "raw_score": 0.5963545028213009,
          "significant": true
        },
        {
          "trait_id": "facet_self_efficacy",
          "name": "Self-efficacy",
          "category": "personality",
          "percentile": 0.7125739092790018,
          "raw_score": 0.7728262647006446,
          "significant": true
        }
      ]
    },
    {
      "trait_id": "big5_extraversion",
      "name": "Extraversion",
      "category": "personality",
      "percentile": 0.5708527244009464,
      "raw_score": 0.558973485171172,
      "significant": true,
      "children": [
        {
          "trait_id": "facet_activity_level",
          "name": "Activity level",
          "category": "personality",
          "percentile": 0.8796080234684027,
          "raw_score": 0.6004018710530079,
          "significant": true
        },
        {
          "trait_id": "facet_assertiveness",
          "name": "Assertiveness",
          "category": "personality",
          "percentile": 0.934932016466266,
          "raw_score": 0.7197223218383253,
          "significant": true
        },
        {
          "trait_id": "facet_cheerfulness",
          "name": "Cheerfulness",
          "category": "personality",
          "percentile": 0.27278363279497486,
          "raw_score": 0.5978546537346584,
          "significant": true
        },
        {
          "trait_id": "facet_excitement_seeking",
          "name": "Excitement-seeking",
          "category": "personality",
          "percentile": 0.06507199640589822,
          "raw_score": 0.5394303176569981,
          "significant": true
        },
        {
          "trait_id": "facet_friendliness",
          "name": "Outgoing",
          "category": "personality",
          "percentile": 0.5898136192711468,
          "raw_score": 0.5718772422591389,
          "significant": true
        },
        {
          "trait_id": "facet_gregariousness",
          "name": "Gregariousness",
          "category": "personality",
          "percentile": 0.17700547570932557,
          "raw_score": 0.40569426950786003,
          "significant": true
        }
      ]
    },
    {
      "trait_id": "big5_agreeableness",
      "name": "Agreeableness",
      "category": "personality",
      "percentile": 0.3830807992405954,
      "raw_score": 0.7303754513881655,
      "significant": true,
      "children": [
        {
          "trait_id": "facet_altruism",
          "name": "Altruism",
          "category": "personality",
          "percentile": 0.8884137611925418,
          "raw_score": 0.7478226357140466,
          "significant": true
        },
        {
          "trait_id": "facet_cooperation",
          "name": "Cooperation",
          "category": "personality",
          "percentile": 0.9355020549629216,
          "raw_score": 0.6708494441236551,
          "significant": true
        },
        {
          "trait_id": "facet_modesty",
          "name": "Modesty",
          "category": "personality",
          "percentile": 0.3112769776487499,
          "raw_score": 0.42240218097005666,
          "significant": true
        },
        {
          "trait_id": "facet_morality",
          "name": "Uncompromising",
          "category": "personality",
          "percentile": 0.9534083966463902,
          "raw_score": 0.7050254401117583,
          "significant": true
        },
        {
          "trait_id": "facet_sympathy",
          "name": "Sympathy",
          "category": "personality",
          "percentile": 0.9905501520175062,
          "raw_score": 0.7531162538128571,
          "significant": true
        },
        {
          "trait_id": "facet_trust",
          "name": "Trust",
          "category": "personality",
          "percentile": 0.9065821990462913,
          "raw_score": 0.6401820408809619,
          "significant": true
        }
      ]
    },
    {
      "trait_id": "big5_neuroticism",
      "name": "Emotional range",
      "category": "personality",
      "percentile": 0.7369123086921805,
      "raw_score": 0.5030973089451426,
      "significant": true,
      "children": [
        {
          "trait_id": "facet_anger",
          "name": "Fiery",
          "category": "personality",
          "percentile": 0.023197316206206908,
          "raw_score": 0.42679334871764224,
          "significant": true
        },
        {
          "trait_id": "facet_anxiety",
          "name": "Prone to worry",
          "category": "personality",
          "percentile": 0.03703623365058134,
          "raw_score": 0.4723006249788457,
          "significant": true
        },
        {
          "trait_id": "facet_depression",
          "name": "Melancholy",
          "category": "personality",
          "percentile": 0.16691714404410474,
          "raw_score": 0.38722772420953294,
          "significant": true
        },
        {
          "trait_id": "facet_immoderation",
          "name": "Immoderation",
          "category": "personality",
          "percentile": 0.16266425802362017,
          "raw_score": 0.46278934279753603,
          "significant": true
        },
        {
          "trait_id": "facet_self_consciousness",
          "name": "Self-consciousness",
          "category": "personality",
          "percentile": 0.30758768123652447,
          "raw_score": 0.5202627833444281,
          "significant": true
        },
        {
          "trait_id": "facet_vulnerability",
          "name": "Susceptible to stress",
          "category": "personality",
          "percentile": 0.10298941604990697,
          "raw_score": 0.3870461855340769,
          "significant": true
        }
      ]
    }
  ],
  "needs": [
    {
      "trait_id": "need_challenge",
      "name": "Challenge",
      "category": "needs",
      "percentile": 0.42292630035342066,
      "raw_score": 0.7230651952660634,
      "significant": true
    },
    {
      "trait_id": "need_closeness",
      "name": "Closeness",
      "category": "needs",
      "percentile": 0.12677184729961438,
      "raw_score": 0.7426811656592102,
      "significant": true
    },
    {
      "trait_id": "need_curiosity",
      "name": "Curiosity",
      "category": "needs",
      "percentile": 0.8410606624471038,
      "raw_score": 0.8429383751234116,
      "significant": true
    },
    {
      "trait_id": "need_excitement",
      "name": "Excitement",
      "category": "needs",
      "percentile": 0.10449266443160693,
      "raw_score": 0.5854053732705335,
      "significant": true
    },
    {
      "trait_id": "need_harmony",
      "name": "Harmony",
      "category": "needs",
      "percentile": 0.08855421108975037,
      "raw_score": 0.7626519378429072,
      "significant": true
    },
    {
      "trait_id": "need_ideal",
      "name": "Ideal",
      "category": "needs",
      "percentile": 0.23228475589348752,
      "raw_score": 0.6562996175062462,
      "significant": true
    },
    {
      "trait_id": "need_liberty",
      "name": "Liberty",
      "category": "needs",
      "percentile": 0.12410192162610528,
      "raw_score": 0.6932534606234582,
      "significant": true
    },
    {
      "trait_id": "need_love",
      "name": "Love",
      "category": "needs",
      "percentile": 0.04713440385383966,
      "raw_score": 0.6872611164012824,
      "significant": true
    },
    {
      "trait_id": "need_practicality",
      "name": "Practicality",
      "category": "needs",
      "percentile": 0.13599795108753465,
      "raw_score": 0.7040400781179945,
      "significant": true
    },
    {
      "trait_id": "need_self_expression",
      "name": "Self-expression",
      "category": "needs",
      "percentile": 0.045793481152447635,
      "raw_score": 0.6168413196982746,
      "significant": true
    },
    {
      "trait_id": "need_stability",
      "name": "Stability",
      "category": "needs",
      "percentile": 0.094996188543707,
      "raw_score": 0.6927102838594119,
      "significant": true
    },
    {
      "trait_id": "need_structure",
      "name": "Structure",
      "category": "needs",
      "percentile": 0.5764983434387869,
      "raw_score": 0.7013067183063875,
      "significant": true
    }
  ],
  "values": [
    {
      "trait_id": "value_conservation",
      "name": "Conservation",
      "category": "values",
      "percentile": 0.05203314548214616,
      "raw_score": 0.5922230083007343,
      "significant": true
    },
    {
      "trait_id": "value_openness_to_change",
      "name": "Openness to change",
      "category": "values",
      "percentile": 0.529827033858143,
      "raw_score": 0.7871538954572774,
      "significant": true
    },
    {
      "trait_id": "value_hedonism",
      "name": "Hedonism",
      "category": "values",
      "percentile": 0.0528156899433459,
      "raw_score": 0.6347929452003138,
      "significant": true
    },
    {
      "trait_id": "value_self_enhancement",
      "name": "Self-enhancement",
      "category": "values",
      "percentile": 0.32333875326493267,
      "raw_score": 0.6862205108284511,
      "significant": true
    },
    {
      "trait_id": "value_self_transcendence",
      "name": "Self-transcendence",
      "category": "values",
      "percentile": 0.14755005542273425,
      "raw_score": 0.8159055387746288,
      "significant": true
    }
  ],
  "warnings": []
}