{
  "word_count": 3430,
  "processed_language": "en",
  "personality": [
    {
      "trait_id": "big5_openness",
      "name": "Openness",
      "category": "personality",
      "percentile": 0.9939204034130661,
      "raw_score": 0.8287079099564941,
      "significant": true,
      "children": [
        {
          "trait_id": "facet_adventurousness",
          "name": "Adventurousness",
          "category": "personality",
          "percentile": 0.9389158756320333,
          "raw_score": 0.5597934798083843,
          "significant": true
        },
        {
          "trait_id": "facet_artistic_interests",
          "name": "Artistic interests",
          "category": "personality",
          "percentile": 0.7518662889677847,
          "raw_score": 0.6997675927197924,
          "significant": true
        },
        {
          "trait_id": "facet_emotionality",
          "name": "Emotionality",
          "category": "personality",
          "percentile": 0.19940401809279423,
          "raw_score": 0.6137963208108035,
          "significant": true
        },
        {
          "trait_id": "facet_imagination",
          "name": "Imagination",
          "category": "personality",
          "percentile": 0.32215704122147615,
          "raw_score": 0.7119271218045867,
          "significant": true
        },
        {
          "trait_id": "facet_intellect",
          "name": "Intellect",
          "category": "personality",
          "percentile": 0.9946197238154777,
          "raw_score": 0.7252962877012589,
          "significant": true
        },
        {
          "trait_id": "facet_liberalism",
          "name": "Authority-challenging",
          "category": "personality",
          "percentile": 0.9908496444283839,
          "raw_score": 0.6350679739178762,
          "significant": true
        }
      ]
    },
    {
      "trait_id": "big5_conscientiousness",
      "name": "Conscientiousness",
      "category": "personality",
      "percentile": 0.6356701746838784,
      "raw_score": 0.6442311379242384,
      "significant": true,
      "children": [
        {
          "trait_id": "facet_achievement_striving",
          "name": "Achievement striving",
          "category": "personality",
          "percentile": 0.705777697092981,
          "raw_score": 0.7170462451056017,
          "significant": true
        },
        {
          "trait_id": "facet_cautiousness",
          "name": "Cautiousness",
          "category": "personality",
          "percentile": 0.9407219853243047,
          "raw_score": 0.5910038173832457,
          "significant": true
        },
        {
          "trait_id": "facet_dutifulness",
          "name": "Dutifulness",
          "category": "personality",
          "percentile": 0.6176081030017767,
          "raw_score": 0.6662278051963711,
          "significant": true
        },
        {
          "trait_id": "facet_orderliness",
          "name": "Orderliness",
          "category": "personality",
          "percentile": 0.18551739402050882,
          "raw_score": 0.46485467217749665,
          "significant": true
        },
        {
          "trait_id": "facet_self_discipline",
          "name": "Self-discipline",
          "category": "personality",
          "percentile": 0.41528578531347027,
          "raw_score": 0.5604608111997867,
          "significant": true
        },
        {
          "trait_id": "facet_self_efficacy",
          "name": "Self-efficacy",
          "category": "personality",
          "percentile": 0.5461002121878948,
          "raw_score": 0.7571727059290517,
          "significant": true
        }
      ]
    },
    {
      "trait_id": "big5_extraversion",
      "name": "Extraversion",
      "category": "personality",
      "percentile": 0.4744544001033105,
      "raw_score": 0.54814679286627,
      "significant": true,
      "children": [
        {
          "trait_id": "facet_activity_level",
          "name": "Activity level",
          "category": "personality",
          "percentile": 0.9592071363866449,
          "raw_score": 0.6294928542224578,
          "significant": true
        },
        {
          "trait_id": "facet_assertiveness",
          "name": "Assertiveness",
          "category": "personality",
          "percentile": 0.9350933267599728,
          "raw_score": 0.7197859302184411,
          "significant": true
        },
        {
          "trait_id": "facet_cheerfulness",
          "name": "Cheerfulness",
          "category": "personality",
          "percentile": 0.07548539044198221,
          "raw_score": 0.5699436782424161,
          "significant": true
        },
        {
          "trait_id": "facet_excitement_seeking",
          "name": "Excitement-seeking",
          "category": "personality",
          "percentile": 0.07897846169048289,
          "raw_score": 0.5437363851295197,
          "significant": true
        },
        {
          "trait_id": "facet_friendliness",
          "name": "Outgoing",
          "category": "personality",
          "percentile": 0.3023425585526748,
          "raw_score": 0.5345243657304063,
          "significant": true
        },
        {
          "trait_id": "facet_gregariousness",
          "name": "Gregariousness",
          "category": "personality",
          "percentile": 0.1893700340590122,
          "raw_score": 0.4080908892682406,
          "significant": true
        }
      ]
    },
    {
      "trait_id": "big5_agreeableness",
      "name": "Agreeableness",
      "category": "personality",
      "percentile": 0.013076282064328981,
      "raw_score": 0.6537867276893075,
      "significant": true,
      "children": [
        {
          "trait_id": "facet_altruism",
          "name": "Altruism",
          "category": "personality",
          "percentile": 0.7413171046637623,
          "raw_score": 0.7278011973521045,
          "significant": true
        },
        {
          "trait_id": "facet_cooperation",
          "name": "Cooperation",
          "category": "personality",
          "percentile": 0.799786306578176,
          "raw_score": 0.6300488221211609,
          "significant": true
        },
        {
          "trait_id": "facet_modesty",
          "name": "Modesty",
          "category": "personality",
          "percentile": 0.19677024084079314,
          "raw_score": 0.40335446249462925,
          "significant": true
        },
        {
          "trait_id": "facet_morality",
          "name": "Uncompromising",
          "category": "personality",
          "percentile": 0.6098862887276904,
          "raw_score": 0.638976338224283,
          "significant": true
        },
        {
          "trait_id": "facet_sympathy",
          "name": "Sympathy",
          "category": "personality",
          "percentile": 0.8999983540850494,
          "raw_score": 0.7124131398903737,
          "significant": true
        },
        {
          "trait_id": "facet_trust",
          "name": "Trust",
          "category": "personality",
          "percentile": 0.9067509176375359,
          "raw_score": 0.6402237054552793,
          "significant": true
        }
      ]
    },
    {
      "trait_id": "big5_neuroticism",
      "name": "Emotional range",
      "category": "personality",
      "percentile": 0.767321620863283,
      "raw_score": 0.5085202465696017,
      "significant": true,
      "children": [
        {
          "trait_id": "facet_anger",
          "name": "Fiery",
          "category": "personality",
          "percentile": 0.03966226051462718,
          "raw_score": 0.4397629569909628,
          "significant": true
        },
        {
          "trait_id": "facet_anxiety",
          "name": "Prone to worry",
          "category": "personality",
          "percentile": 0.09286577894235187,
          "raw_score": 0.503865860429545,
          "significant": true
        },
        {
          "trait_id": "facet_depression",
          "name": "Melancholy",
          "category": "personality",
          "percentile": 0.5934001812545227,
          "raw_score": 0.4634056782544518,
          "significant": true
        },
        {
          "trait_id": "facet_immoderation",
          "name": "Immoderation",
          "category": "personality",
          "percentile": 0.2558598450263312,
          "raw_score": 0.4753729595675403,
          "significant": true
        },
        {
          "trait_id": "facet_self_consciousness",
          "name": "Self-consciousness",
          "category": "personality",
          "percentile": 0.4126600069175286,
          "raw_score": 0.535101040507037,
          "significant": true
        },
        {
          "trait_id": "facet_vulnerability",
          "name": "Susceptible to stress",
          "category": "personality",
          "percentile": 0.14812783145183483,
          "raw_score": 0.40107562733099544,
          "significant": true
        }
      ]
    }
  ],
  "needs": [
    {
      "trait_id": "need_challenge",
      "name": "Challenge",
      "category": "needs",
      "percentile": 0.15985501084219356,
      "raw_score": 0.687157640144247,
      "significant": true
    },
    {
      "trait_id": "need_closeness",
      "name": "Closeness",
      "category": "needs",
      "percentile": 0.03362829915478449,
      "raw_score": 0.7121356428247746,
      "significant": true
    },
    {
      "trait_id": "need_curiosity",
      "name": "Curiosity",
      "category": "needs",
      "percentile": 0.689531285496706,
      "raw_score": 0.8296655763245435,
      "significant": true
    },
    {
      "trait_id": "need_excitement",
      "name": "Excitement",
      "category": "needs",
      "percentile": 0.12205332501578642,
      "raw_score": 0.5926798208103237,
      "significant": true
    },
    {
      "trait_id": "need_harmony",
      "name": "Harmony",
      "category": "needs",
      "percentile": 0.012559370894098587,
      "raw_score": 0.7319249606335808,
      "significant": true
    },
    {
      "trait_id": "need_ideal",
      "name": "Ideal",
      "category": "needs",
      "percentile": 0.10702754089374139,
      "raw_score": 0.6320087983523401,
      "significant": true
    },
    {
      "trait_id": "need_liberty",
      "name": "Liberty",
      "category": "needs",
      "percentile": 0.17311145017040747,
      "raw_score": 0.7012246951812847,
      "significant": true
    },
    {
      "trait_id": "need_love",
      "name": "Love",
      "category": "needs",
      "percentile": 0.02568421452209424,
      "raw_score": 0.67387907381374,
      "significant": true
    },
    {
      "trait_id": "need_practicality",
      "name": "Practicality",
      "category": "needs",
      "percentile": 0.24280405931187615,
      "raw_score": 0.7127075116602092,
      "significant": true
    },
    {
      "trait_id": "need_self_expression",
      "name": "Self-expression",
      "category": "needs",
      "percentile": 0.03593256787103849,
      "raw_score": 0.6129471677181301,
      "significant": true
    },
    {
      "trait_id": "need_stability",
      "name": "Stability",
      "category": "needs",
      "percentile": 0.031341016610501926,
      "raw_score": 0.6751677209556857,
      "significant": true
    },
    {
      "trait_id": "need_structure",
      "name": "Structure",
      "category": "needs",
      "percentile": 0.5883914067111979,
      "raw_score": 0.702132241895632,
      "significant": true
    }
  ],
  "values": [
    {
      "trait_id": "value_conservation",
      "name": "Conservation",
      "category": "values",
      "percentile": 0.009905985529779171,
      "raw_score": 0.5604880681856925,
      "significant": true
    },
    {
      "trait_id": "value_openness_to_change",
      "name": "Openness to change",
      "category": "values",
      "percentile": 0.7885333640811825,
      "raw_score": 0.8151689415187823,
      "significant": true
    },
    {
      "trait_id": "value_hedonism",
      "name": "Hedonism",
      "category": "values",
      "percentile": 0.039931183168242346,
      "raw_score": 0.6262723712518612,
      "significant": true
    },
    {
      "trait_id": "value_self_enhancement",
      "name": "Self-enhancement",
      "category": "values",
      "percentile": 0.22029519860384456,
      "raw_score": 0.6724966330496093,
      "significant": true
    },
    {
      "trait_id": "value_self_transcendence",
      "name": "Self-transcendence",
      "category": "values",
      "percentile": 0.17149856666390612,
      "raw_score": 0.8175137713488152,
      "significant": true
    }
  ],
  "warnings": []
}