{
  "word_count": 1618,
  "processed_language": "en",
  "personality": [
    {
      "trait_id": "big5_openness",
      "name": "Openness",
      "category": "personality",
      "percentile": 0.993361965781376,
      "raw_score": 0.8277113572035917,
      "significant": true,
      "children": [
        {
          "trait_id": "facet_adventurousness",
          "name": "Adventurousness",
          "category": "personality",
          "percentile": 0.9184618722713287,
          "raw_score": 0.5544252455335055,
          "significant": true
        },
        {
          "trait_id": "facet_artistic_interests",
          "name": "Artistic interests",
          "category": "personality",
          "percentile": 0.5454758142817292,
          "raw_score": 0.6711079062580448,
          "significant": true
        },
        {
          "trait_id": "facet_emotionality",
          "name": "Emotionality",
          "category": "personality",
          "percentile": 0.12089792222530593,
          "raw_score": 0.6004747949364999,
          "significant": true
        },
        {
          "trait_id": "facet_imagination",
          "name": "Imagination",
          "category": "personality",
          "percentile": 0.13343001464091614,
          "raw_score": 0.6797085680221253,
          "significant": true
        },
        {
          "trait_id": "facet_intellect",
          "name": "Intellect",
          "category": "personality",
          "percentile": 0.9957824157823411,
          "raw_score": 0.7291730870294921,
          "significant": true
        },
        {
          "trait_id": "facet_liberalism",
          "name": "Authority-challenging",
          "category": "personality",
          "percentile": 0.9942500365802105,
          "raw_score": 0.6435120227038935,
          "significant": true
        }
      ]
    },
    {
      "trait_id": "big5_conscientiousness",
      "name": "Conscientiousness",
      "category": "personality",
      "percentile": 0.7136587693998739,
      "raw_score": 0.6543613569195534,
      "significant": true,
      "children": [
        {
          "trait_id": "facet_achievement_striving",
          "name": "Achievement striving",
          "category": "personality",
          "percentile": 0.7666377600141572,
          "raw_score": 0.7269324313130794,
          "significant": true
        },
        {
          "trait_id": "facet_cautiousness",
          "name": "Cautiousness",
          "category": "personality",
          "percentile": 0.9628875812623697,
          "raw_score": 0.6051667501443012,
          "significant": true
        },
        {
          "trait_id": "facet_dutifulness",
          "name": "Dutifulness",
          "category": "personality",
          "percentile": 0.6913908543785581,
          "raw_score": 0.6711402233555849,
          "significant": true
        },
        {
          "trait_id": "facet_orderliness",
          "name": "Orderliness",
          "category": "personality",
          "percentile": 0.18486256994243028,
          "raw_score": 0.4647743675866202,
          "significant": true
        },
        {
          "trait_id": "facet_self_discipline",
          "name": "Self-discipline",
          "category": "personality",
          "percentile": 0.605244425627895,
          "raw_score": 0.5833697585834361,
          "significant": true
        },
        {
          "trait_id": "facet_self_efficacy",
          "name": "Self-efficacy",
          "category": "personality",
          "percentile": 0.5687310734973936,
          "raw_score": 0.7591888998821105,
          "significant": true
        }
      ]
    },
    {
      "trait_id": "big5_extraversion",
      "name": "Extraversion",
      "category": "personality",
      "percentile": 0.7772897306944426,
      "raw_score": 0.5850571395013449,
      "significant": true,
      "children": [
        {
          "trait_id": "facet_activity_level",
          "name": "Activity level",
          "category": "personality",
          "percentile": 0.9433502924967871,
          "raw_score": 0.6214070062793728,
          "significant": true
        },
        {
          "trait_id": "facet_assertiveness",
          "name": "Assertiveness",
          "category": "personality",
          "percentile": 0.9475932184902303,
          "raw_score": 0.7251405843292865,
          "significant": true
        },
        {
          "trait_id": "facet_cheerfulness",
          "name": "Cheerfulness",
          "category": "personality",
          "percentile": 0.10432871383901698,
          "raw_score": 0.5759455691235014,
          "significant": true
        },
        {
          "trait_id": "facet_excitement_seeking",
          "name": "Excitement-seeking",
          "category": "personality",
          "percentile": 0.038562258654728065,
          "raw_score": 0.5286570754271471,
          "significant": true
        },
        {
          "trait_id": "facet_friendliness",
          "name": "Outgoing",
          "category": "personality",
          "percentile": 0.3955587566084883,
          "raw_score": 0.5472044519785256,
          "significant": true
        },
        {
          "trait_id": "facet_gregariousness",
          "name": "Gregariousness",
          "category": "personality",
          "percentile": 0.17790704938141,
          "raw_score": 0.4058724998779791,
          "significant": true
        }
      ]
    },
    {
      "trait_id": "big5_agreeableness",
      "name": "Agreeableness",
      "category": "personality",
      "percentile": 0.10861945751092106,
      "raw_score": 0.6931451489799894,
      "significant": true,
      "children": [
        {
          "trait_id": "facet_altruism",
          "name": "Altruism",
          "category": "personality",
          "percentile": 0.6212495705110099,
          "raw_score": 0.7159212029271442,
          "significant": true
        },
        {
          "trait_id": "facet_cooperation",
          "name": "Cooperation",
          "category": "personality",
          "percentile": 0.8701117102185807,
          "raw_score": 0.6472833333917124,
          "significant": true
        },
        {
          "trait_id": "facet_modesty",
          "name": "Modesty",
          "category": "personality",
          "percentile": 0.18085703274798737,
          "raw_score": 0.4002470595452935,
          "significant": true
        },
        {
          "trait_id": "facet_morality",
          "name": "Uncompromising",
          "category": "personality",
          "percentile": 0.7791384572256163,
          "raw_score": 0.662108999985823,
          "significant": true
        },
        {
          "trait_id": "facet_sympathy",
          "name": "Sympathy",
          "category": "personality",
          "percentile": 0.804067368807377,
          "raw_score": 0.6961732074088985,
          "significant": true
        },
        {
          "trait_id": "facet_trust",
          "name": "Trust",
          "category": "personality",
          "percentile": 0.8935748160937101,
          "raw_score": 0.6371238734086502,
          "significant": true
        }
      ]
    },
    {
      "trait_id": "big5_neuroticism",
      "name": "Emotional range",
      "category": "personality",
      "percentile": 0.8297595235612472,
      "raw_score": 0.5211002040324562,
      "significant": true,
      "children": [
        {
          "trait_id": "facet_anger",
          "name": "Fiery",
          "category": "personality",
          "percentile": 0.02635941374715728,
          "raw_score": 0.4297774506858656,
          "significant": true
        },
        {
          "trait_id": "facet_anxiety",
          "name": "Prone to worry",
          "category": "personality",
          "percentile": 0.03271426064023453,
          "raw_score": 0.46847112875171204,
          "significant": true
        },
        {
          "trait_id": "facet_depression",
          "name": "Melancholy",
          "category": "personality",
          "percentile": 0.32950058273073324,
          "raw_score": 0.4204882494307257,
          "significant": true
        },
        {
          "trait_id": "facet_immoderation",
          "name": "Immoderation",
          "category": "personality",
          "percentile": 0.2333012141364325,
          "raw_score": 0.4726112167104751,
          "significant": true
        },
        {
          "trait_id": "facet_self_consciousness",
          "name": "Self-consciousness",
          "category": "personality",
          "percentile": 0.2697016488143031,
          "raw_score": 0.5144211974750257,
          "significant": true
        },
        {
          "trait_id": "facet_vulnerability",
          "name": "Susceptible to stress",
          "category": "personality",
          "percentile": 0.0840803994289212,
          "raw_score": 0.3798189417001371,
          "significant": true
        }
      ]
    }
  ],
  "needs": [
    {
      "trait_id": "need_challenge",
      "name": "Challenge",
      "category": "needs",
      "percentile": 0.22375925982442413,
      "raw_score": 0.6977192583543048,
      "significant": true
    },
    {
      "trait_id": "need_closeness",
      "name": "Closeness",
      "category": "needs",
      "percentile": 0.030113310572374985,
      "raw_score": 0.7099529162934335,
      "significant": true
    },
    {
      "trait_id": "need_curiosity",
      "name": "Curiosity",
      "category": "needs",
      "percentile": 0.5558041554803731,
      "raw_score": 0.8203438368470592,
      "significant": true
    },
    {
      "trait_id": "need_excitement",
      "name": "Excitement",
      "category": "needs",
      "percentile": 0.04488055023991894,
      "raw_score": 0.5504300727677331,
      "significant": true
    },
    {
      "trait_id": "need_harmony",
      "name": "Harmony",
      "category": "needs",
      "percentile": 0.0070488416109466545,
      "raw_score": 0.7244943179124695,
      "significant": true
    },
    {
      "trait_id": "need_ideal",
      "name": "Ideal",
      "category": "needs",
      "percentile": 0.07996419007686223,
      "raw_score": 0.624271242342639,
      "significant": true
    },
    {
      "trait_id": "need_liberty",
      "name": "Liberty",
      "category": "needs",
      "percentile": 0.07661008637418742,
      "raw_score": 0.6830066441353042,
      "significant": true
    },
    {
      "trait_id": "need_love",
      "name": "Love",
      "category": "needs",
      "percentile": 0.02356870062723926,
      "raw_score": 0.6720950161916284,
      "significant": true
    },
    {
      "trait_id": "need_practicality",
      "name": "Practicality",
      "category": "needs",
      "percentile": 0.2506224053591695,
      "raw_score": 0.7132428692979063,
      "significant": true
    },
    {
      "trait_id": "need_self_expression",
      "name": "Self-expression",
      "category": "needs",
      "percentile": 0.03177186228109902,
      "raw_score": 0.6110362048331716,
      "significant": true
    },
    {
      "trait_id": "need_stability",
      "name": "Stability",
      "category": "needs",
      "percentile": 0.008264050324119199,
      "raw_score": 0.6581104553217256,
      "significant": true
    },
    {
      "trait_id": "need_structure",
      "name": "Structure",
      "category": "needs",
      "percentile": 0.5213052855960524,
      "raw_score": 0.6975263377614488,
      "significant": true
    }
  ],
  "values": [
    {
      "trait_id": "value_conservation",
      "name": "Conservation",
      "category": "values",
      "percentile": 0.0070080503710875375,
      "raw_score": 0.5547684917931405,
      "significant": true
    },
    {
      "trait_id": "value_openness_to_change",
      "name": "Openness to change",
      "category": "values",
      "percentile": 0.5339686801028248,
      "raw_score": 0.7875555079985924,
      "significant": true
    },
    {
      "trait_id": "value_hedonism",
      "name": "Hedonism",
      "category": "values",
      "percentile": 0.01694048065946052,
      "raw_score": 0.6026289982059363,
      "significant": true
    },
    {
      "trait_id": "value_self_enhancement",
      "name": "Self-enhancement",
      "category": "values",
      "percentile": 0.14759242532947314,
      "raw_score": 0.660404604199272,
      "significant": true
    },
    {
      "trait_id": "value_self_transcendence",
      "name": "Self-transcendence",
      "category": "values",
      "percentile": 0.08689598297628331,
      "raw_score": 0.8108055061658552,
      "significant": true
    }
  ],
  "warnings": []
}